odoo/addons/ssi_field_date_callable_attribute/README.rst
odoo/addons/ssi_field_date_callable_attribute/__init__.py
odoo/addons/ssi_field_date_callable_attribute/__manifest__.py
odoo/addons/ssi_field_date_callable_attribute/fields.py
odoo/addons/ssi_field_date_callable_attribute/static/description/icon.png
odoo14_addon_ssi_field_date_callable_attribute-14.0.1.1.0.dist-info/METADATA
odoo14_addon_ssi_field_date_callable_attribute-14.0.1.1.0.dist-info/WHEEL
odoo14_addon_ssi_field_date_callable_attribute-14.0.1.1.0.dist-info/top_level.txt
odoo14_addon_ssi_field_date_callable_attribute-14.0.1.1.0.dist-info/RECORD
